rokugu/AutoLayout.py
rokugu/ElidedLabelWidget.py
rokugu/FlowLayout.py
rokugu/ImageWidget.py
rokugu/ListWidget.py
rokugu/StackWidget.py
rokugu/SvgWidget.py
rokugu/Widget.py
rokugu/Window.py
rokugu/__init__.py
rokugu/os.py
rokugu/support.py
rokugu-0.1.0.dist-info/licenses/LICENSE
rokugu-0.1.0.dist-info/METADATA
rokugu-0.1.0.dist-info/WHEEL
rokugu-0.1.0.dist-info/top_level.txt
rokugu-0.1.0.dist-info/RECORD
