Metadata-Version: 2.4
Name: rokugu
Version: 0.1.0
Summary: An opinionated PySide6 library that delivers ready-to-use components and utilities.
Author-email: Santos Vilanculos <santosvilanculos@yahoo.com>
License: MIT
Project-URL: Homepage, https://github.com/rokugu
Project-URL: Documentation, https://rokugu.readthedocs.com
Project-URL: Repository, https://github.com/rokugu/rokugu
Project-URL: Bug Tracker, https://github.com/rokugu/rokugu/issues
Project-URL: Changelog, https://github.com/rokugu/rokugu/blob/main/CHANGELOG.md
Keywords: PySide6
Classifier: Development Status :: 2 - Pre-Alpha
Classifier: Intended Audience :: Developers
Classifier: License :: OSI Approved :: MIT License
Classifier: Natural Language :: English
Classifier: Operating System :: OS Independent
Classifier: Programming Language :: Python :: 3
Classifier: Programming Language :: Python :: 3.12
Classifier: Programming Language :: Python :: 3.13
Classifier: Typing :: Typed
Requires-Python: <3.14,>=3.12
License-File: LICENSE
Requires-Dist: pendulum>=3.0.0
Requires-Dist: psutil>=7.0.0
Requires-Dist: PySide6>=6.8.2.1
Provides-Extra: dev
Requires-Dist: autoflake==2.3.1; extra == "dev"
Requires-Dist: black==25.1.0; extra == "dev"
Requires-Dist: build==1.2.2; extra == "dev"
Requires-Dist: isort==6.0.0; extra == "dev"
Requires-Dist: pendulum==3.0.0; extra == "dev"
Requires-Dist: pillow==11.1.0; extra == "dev"
Requires-Dist: pyinstaller==6.12.0; extra == "dev"
Requires-Dist: pyinstaller_versionfile==3.0.0; extra == "dev"
Requires-Dist: PySide6==6.8.2.1; extra == "dev"
Requires-Dist: psutil==7.0.0; extra == "dev"
Requires-Dist: py-mon==2.0.5; extra == "dev"
Requires-Dist: taskipy; extra == "dev"
Requires-Dist: twine==6.1.0; extra == "dev"
Requires-Dist: wheel==0.45.1; extra == "dev"
Provides-Extra: doc
Requires-Dist: mkdocs==1.6.1; extra == "doc"
Requires-Dist: mkdocs-material==9.6.8; extra == "doc"
Requires-Dist: mkdocstrings==0.29.0; extra == "doc"
Requires-Dist: mkdocstrings-python==1.16.5; extra == "doc"
Requires-Dist: pymdown-extensions==10.14.3; extra == "doc"
Dynamic: license-file
